{
  "$schema": "https://json.schemastore.org/dtcg",
  "$version": "1.0.0",
  "$metadata": {
    "tokenSetOrder": [
      "color-Primitivos"
    ]
  },
  "color-Primitivos": {
    "Primario": {
      "$value": {
        "r": 0.125490203499794,
        "g": 1,
        "b": 0.35686275362968445,
        "a": 1
      },
      "$type": "color",
      "$description": "",
      "$extensions": {
        "com.figma": {
          "id": "VariableID:1:3",
          "name": "Primario"
        }
      }
    },
    "verde": {
      "100": {
        "$value": {
          "r": 0,
          "g": 0.20000000298023224,
          "b": 0.05291479825973511,
          "a": 1
        },
        "$type": "color",
        "$description": "",
        "$extensions": {
          "com.figma": {
            "id": "VariableID:3:7",
            "name": "verde/100"
          }
        }
      },
      "500": {
        "$value": {
          "r": 0.125490203499794,
          "g": 1,
          "b": 0.35686275362968445,
          "a": 1
        },
        "$type": "color",
        "$description": "",
        "$extensions": {
          "com.figma": {
            "id": "VariableID:3:5",
            "name": "verde/500"
          }
        }
      },
      "900": {
        "$value": {
          "r": 0.6000000238418579,
          "g": 1,
          "b": 0.7058296203613281,
          "a": 1
        },
        "$type": "color",
        "$description": "",
        "$extensions": {
          "com.figma": {
            "id": "VariableID:3:8",
            "name": "verde/900"
          }
        }
      }
    },
    "radio": {
      "$value": 20,
      "$type": "dimension",
      "$description": "",
      "$extensions": {
        "com.figma": {
          "id": "VariableID:3:2",
          "name": "radio"
        }
      }
    },
    "fuente": {
      "$value": "Monserrat",
      "$type": "string",
      "$description": "",
      "$extensions": {
        "com.figma": {
          "id": "VariableID:3:3",
          "name": "fuente"
        }
      }
    },
    "activo": {
      "$value": false,
      "$type": "boolean",
      "$description": "",
      "$extensions": {
        "com.figma": {
          "id": "VariableID:3:4",
          "name": "activo"
        }
      }
    }
  }
}